ooxmilker/.DS_Store
ooxmilker/__init__.py
ooxmilker/ooxmilker.py
ooxmilker/formats/__init__.py
ooxmilker/formats/docx_module.py
ooxmilker/formats/pptx_module.py
ooxmilker/formats/vsdx_module.py
ooxmilker/formats/xlsx_module.py
ooxmilker-0.0.3.dist-info/METADATA
ooxmilker-0.0.3.dist-info/WHEEL
ooxmilker-0.0.3.dist-info/licenses/LICENSE
ooxmilker-0.0.3.dist-info/RECORD
