Metadata-Version: 2.1
Name: ooxmilker
Version: 0.0.3
Summary: An Office Open XML parser that outputs HTML.
Author-email: Herve Leleu <mhank42@yahoo.com>
License-File: LICENSE
Classifier: Development Status :: 3 - Alpha
Classifier: License :: OSI Approved :: Apache Software License
Classifier: Operating System :: OS Independent
Classifier: Programming Language :: Python :: 3.6
Classifier: Topic :: Text Processing
Requires-Python: >=3.6
